PyAgent/PYAI ASSISTANCE SERVER.py
PyAgent/PYAS.py
PyAgent/__init__.py
pyaitk/FrameClassifier.pth
pyaitk/FrameClassifierDimension.json
pyaitk/GetWeatherNews.py
pyaitk/NERDimension.json
pyaitk/NERModel.pth
pyaitk/Search.py
pyaitk/__init__.py
pyaitk/core.py
pyaitk/dimensions.json
pyaitk/intents.json
pyaitk/model.pth
pyaitk/Camera/__init__.py
pyaitk/Camera/count_finger.py
pyaitk/Camera/mainCamera.py
pyaitk/Context/__init__.py
pyaitk/Context/mainContext.py
pyaitk/Data/__init__.py
pyaitk/GUI/__init__.py
pyaitk/GUI/core.py
pyaitk/Grammar/__init__.py
pyaitk/Grammar/grammer.py
pyaitk/ITT/__init__.py
pyaitk/ITT/mainitt.py
pyaitk/MathAI/__init__.py
pyaitk/MathAI/mathai.py
pyaitk/Memory/__init__.py
pyaitk/Memory/memory.py
pyaitk/PPTExtract/__init__.py
pyaitk/PTT/__init__.py
pyaitk/STT/__init__.py
pyaitk/STT/mainstt.py
pyaitk/TTI/__init__.py
pyaitk/TTI/maintti.py
pyaitk/TTS/__init__.py
pyaitk/TTS/main.py
pyaitk/TTS/save.py
pyaitk/UDS/__init__.py
pyaitk/UDS/updateDataset.py
pyaitk/eye/__init__.py
pyaitk/eye/eye.py
pyaitk/eye/yolov8n.pt
pythonaibrain-1.1.8.dist-info/licenses/LICENSE.txt
pythonaibrain-1.1.8.dist-info/METADATA
pythonaibrain-1.1.8.dist-info/WHEEL
pythonaibrain-1.1.8.dist-info/top_level.txt
pythonaibrain-1.1.8.dist-info/RECORD
