Metadata-Version: 2.4
Name: pythonaibrain
Version: 1.1.8
Summary: PythonAIBrain is a versatile, plug-and-play Python package designed to help you build offline intelligent AI assistants and applications effortlessly. With modules covering speech recognition, text-to-speech, image generation, natural language understanding, and more, PythonAIBrain lets you create powerful AI solutions without deep expertise or complex setup. Whether you’re a beginner or an experienced developer, get ready to bring your AI ideas to life quickly and efficiently.
Author-email: Divyanshu Sinha <divyanshu.sinha136@gmail.com>
Project-URL: Homepage, https://pypi.org/project/pythonaibrain
Project-URL: Repository, https://github.com/World-Of-Programming-And-Technology/PythonAI
Project-URL: Issues, https://github.com/World-Of-Programming-And-Technology/PythonAI/issues
Keywords: AI Assistant,Machine Learning,Natural Language Processing,Text to Speech,Speech Recognition,Image Generation,Computer Vision,Chatbot,Voice Assistant,AI Framework,AI Modules,Easy AI,Plug and Play AI,Python Package,AI Library,AI Toolkit,Python Automation,Smart Assistant,Python Developer,Biggner Friendly,AI Starter Kit,Open Source AI,Offline Chatbot,Python AI Tool Kit,AI Tools,Advance Chatbot,Advance Chatbot tools kit
Classifier: Programming Language :: Python :: 3
Classifier: License :: OSI Approved :: GNU Lesser General Public License v2 or later (LGPLv2+)
Classifier: Operating System :: OS Independent
Classifier: Topic :: Scientific/Engineering :: Artificial Intelligence
Classifier: Intended Audience :: Developers
Requires-Python: >=3.9
License-File: LICENSE.txt
Requires-Dist: nltk
Requires-Dist: pyjokes
Requires-Dist: yfinance
Requires-Dist: numpy
Requires-Dist: scikit-learn
Requires-Dist: torch
Requires-Dist: flask
Requires-Dist: flask-limiter
Requires-Dist: opencv-python
Requires-Dist: Pillow
Requires-Dist: pyzbar
Requires-Dist: ultralytics
Requires-Dist: sympy
Requires-Dist: PyMuPDF
Requires-Dist: pyttsx3
Requires-Dist: requests
Requires-Dist: beautifulsoup4
Requires-Dist: tokenizers
Requires-Dist: customtkinter
Requires-Dist: python-multipart
Requires-Dist: easyocr
Requires-Dist: python-pptx
Provides-Extra: test
Requires-Dist: pytest; extra == "test"
Provides-Extra: docs
Requires-Dist: sphinx; extra == "docs"
Dynamic: license-file
